mosaiq/__init__.py
mosaiq-0.3.6.dist-info/LICENSE
mosaiq-0.3.6.dist-info/LICENSE.md
mosaiq-0.3.6.dist-info/METADATA
mosaiq-0.3.6.dist-info/WHEEL
mosaiq-0.3.6.dist-info/top_level.txt
mosaiq-0.3.6.dist-info/RECORD
