Metadata-Version: 2.1
Name: mosaiq
Version: 0.3.6
Summary: A generalized mosaic plotting function for categorical and numerical data.
Author-email: Justin Donaldson <jjd@jjd.io>
License: MIT
Project-URL: Homepage, https://github.com/jdonaldson/mosaiq-python
Requires-Python: >=3.12
License-File: LICENSE
License-File: LICENSE.md
Requires-Dist: altair
Requires-Dist: pandas
Requires-Dist: narwhals
Requires-Dist: build
Requires-Dist: idna
Requires-Dist: matplotlib
Requires-Dist: bump-my-version
Requires-Dist: statsmodels
Provides-Extra: ci
Requires-Dist: pytest-cov ; extra == 'ci'
Provides-Extra: dev
Requires-Dist: mosaiq[ci] ; extra == 'dev'
